airflow/providers/cncf/kubernetes/__init__.py
airflow/providers/cncf/kubernetes/backcompat/__init__.py
airflow/providers/cncf/kubernetes/backcompat/backwards_compat_converters.py
airflow/providers/cncf/kubernetes/example_dags/__init__.py
airflow/providers/cncf/kubernetes/example_dags/example_kubernetes.py
airflow/providers/cncf/kubernetes/example_dags/example_spark_kubernetes.py
airflow/providers/cncf/kubernetes/example_dags/example_spark_kubernetes_spark_pi.yaml
airflow/providers/cncf/kubernetes/hooks/__init__.py
airflow/providers/cncf/kubernetes/hooks/kubernetes.py
airflow/providers/cncf/kubernetes/operators/__init__.py
airflow/providers/cncf/kubernetes/operators/kubernetes_pod.py
airflow/providers/cncf/kubernetes/operators/spark_kubernetes.py
airflow/providers/cncf/kubernetes/sensors/__init__.py
airflow/providers/cncf/kubernetes/sensors/spark_kubernetes.py
apache_airflow_backport_providers_cncf_kubernetes-2021.3.3.dist-info/LICENSE
apache_airflow_backport_providers_cncf_kubernetes-2021.3.3.dist-info/METADATA
apache_airflow_backport_providers_cncf_kubernetes-2021.3.3.dist-info/NOTICE
apache_airflow_backport_providers_cncf_kubernetes-2021.3.3.dist-info/WHEEL
apache_airflow_backport_providers_cncf_kubernetes-2021.3.3.dist-info/top_level.txt
apache_airflow_backport_providers_cncf_kubernetes-2021.3.3.dist-info/RECORD
